taskiq_dependencies/__init__.py
taskiq_dependencies/ctx.py
taskiq_dependencies/dependency.py
taskiq_dependencies/graph.py
taskiq_dependencies/py.typed
taskiq_dependencies/utils.py
taskiq_dependencies-1.5.6.dist-info/LICENSE
taskiq_dependencies-1.5.6.dist-info/METADATA
taskiq_dependencies-1.5.6.dist-info/WHEEL
taskiq_dependencies-1.5.6.dist-info/RECORD
