Metadata-Version: 2.1
Name: taskiq-dependencies
Version: 1.5.6
Summary: FastAPI like dependency injection implementation
Keywords: taskiq,dependencies,injection,async,DI
Author: Pavel Kirilin
Author-email: win10@list.ru
Requires-Python: >=3.9,<4.0
Classifier: Intended Audience :: Developers
Classifier: Operating System :: OS Independent
Classifier: Programming Language :: Python
Classifier: Programming Language :: Python :: 3
Classifier: Programming Language :: Python :: 3.9
Classifier: Programming Language :: Python :: 3.10
Classifier: Programming Language :: Python :: 3.11
Classifier: Programming Language :: Python :: 3.12
Classifier: Programming Language :: Python :: 3.13
Classifier: Programming Language :: Python :: 3 :: Only
Classifier: Programming Language :: Python :: 3.8
Classifier: Typing :: Typed
Requires-Dist: typing-extensions (>=4.6.3) ; python_version < "3.10"
